{
    "version": 1,
    "updatedAt": "2026-04-11T18:20:00+00:00",
    "items": [
        {
            "id": "ach_beginner_1",
            "title": "Beginner",
            "target": 1,
            "image": "assets\/avatars\/beginner.png",
            "titleReward": "Der Aufsteiger",
            "active": true
        },
        {
            "id": "ach_holz_10",
            "title": "Bronze",
            "target": 10,
            "image": "assets\/avatars\/holz.png",
            "titleReward": "Bronzeanwaerter",
            "active": true
        },
        {
            "id": "ach_silber_50",
            "title": "Silber",
            "target": 50,
            "image": "assets\/avatars\/silber.png",
            "titleReward": "Silberritter",
            "active": true
        },
        {
            "id": "ach_gold_200",
            "title": "Gold",
            "target": 200,
            "image": "assets\/avatars\/gold.png",
            "titleReward": "Goldchampion",
            "active": true
        },
        {
            "id": "ach_elite_400",
            "title": "Platin",
            "target": 400,
            "image": "assets\/avatars\/elite.png",
            "titleReward": "Platinheld",
            "active": true
        },
        {
            "id": "ach_smaragd_600",
            "title": "Smaragd",
            "target": 600,
            "image": "assets\/avatars\/smaragd.png",
            "titleReward": "Smaragdwaechter",
            "active": true
        },
        {
            "id": "ach_rubin_800",
            "title": "Rubin",
            "target": 800,
            "image": "assets\/avatars\/rubin.png",
            "titleReward": "Rubinlegende",
            "active": true
        },
        {
            "id": "ach_diamant_1000",
            "title": "Diamant",
            "target": 1000,
            "image": "assets\/avatars\/diamant.png",
            "titleReward": "Diamantmeister",
            "active": true
        },
        {
            "id": "ach_meister_1500",
            "title": "Meister",
            "target": 1500,
            "image": "assets\/avatars\/meister.png",
            "titleReward": "Grossmeister",
            "active": true
        },
        {
            "id": "ach_grossmeister_2000",
            "title": "Legende",
            "target": 2000,
            "image": "assets\/avatars\/grossmeister.png",
            "titleReward": "Unsterbliche Legende",
            "active": true
        },
        {
            "id": "ach_wohl_gekleidet_custom",
            "title": "Wohl gekleidet",
            "image": "assets\\deinbild.png",
            "systemManaged": false,
            "unlockConditionType": "quest_ids",
            "unlockConditionValue": null,
            "unlockConditionQuestIds": [
                39,
                40
            ],
            "unlockConditionRewardIds": [],
            "titleReward": "Derwohl gekleidete",
            "active": true
        }
    ]
}